pacifica_uniqueid-0.5.1-py3.8-nspkg.pth
pacifica/uniqueid/__init__.py
pacifica/uniqueid/__main__.py
pacifica/uniqueid/config.py
pacifica/uniqueid/globals.py
pacifica/uniqueid/orm.py
pacifica/uniqueid/rest.py
pacifica/uniqueid/wsgi.py
pacifica_uniqueid-0.5.1.dist-info/LICENSE
pacifica_uniqueid-0.5.1.dist-info/METADATA
pacifica_uniqueid-0.5.1.dist-info/WHEEL
pacifica_uniqueid-0.5.1.dist-info/entry_points.txt
pacifica_uniqueid-0.5.1.dist-info/namespace_packages.txt
pacifica_uniqueid-0.5.1.dist-info/top_level.txt
pacifica_uniqueid-0.5.1.dist-info/RECORD
