Metadata-Version: 2.1
Name: pacifica-uniqueid
Version: 0.5.1
Summary: Pacifica UniqueID
Home-page: https://github.com/pacifica/pacifica-uniqueid/
Author: David Brown
Author-email: david.brown@pnnl.gov
License: UNKNOWN
Platform: UNKNOWN
Requires-Dist: cherrypy
Requires-Dist: pacifica-namespace
Requires-Dist: peewee (>2)
